feedwerk/__init__.py
feedwerk/_compat.py
feedwerk/atom.py
feedwerk-0.0.3.dist-info/LICENSE.rst
feedwerk-0.0.3.dist-info/METADATA
feedwerk-0.0.3.dist-info/WHEEL
feedwerk-0.0.3.dist-info/top_level.txt
feedwerk-0.0.3.dist-info/RECORD
