Metadata-Version: 2.1
Name: feedwerk
Version: 0.0.3
Summary: The atom feed generator from werkzeug.
Home-page: https://github.com/uniphil/feedwerk
Author: phil
Author-email: phil@commit--blog.com
License: BSD-3-Clause
Project-URL: Documentation, https://github.com/uniphil/feedwerk
Project-URL: Code, https://github.com/uniphil/feedwerk
Project-URL: Issue tracker, https://github.com/uniphil/feedwerk/issues
Platform: UNKNOWN
Classifier: Environment :: Web Environment
Classifier: Intended Audience :: Developers
Classifier: License :: OSI Approved :: BSD License
Classifier: Operating System :: OS Independent
Classifier: Topic :: Internet :: WWW/HTTP :: Dynamic Content
Classifier: Topic :: Software Development :: Libraries :: Python Modules
Requires-Python: >=2.7, !=3.0.*, !=3.1.*, !=3.2.*, !=3.3.*
License-File: LICENSE.rst
Requires-Dist: werkzeug (>=1.0.0)
Provides-Extra: dev
Requires-Dist: pytest ; extra == 'dev'
